TracTicketGuidelines-1.0.0.dist-info/DESCRIPTION.rst
TracTicketGuidelines-1.0.0.dist-info/METADATA
TracTicketGuidelines-1.0.0.dist-info/RECORD
TracTicketGuidelines-1.0.0.dist-info/WHEEL
TracTicketGuidelines-1.0.0.dist-info/entry_points.txt
TracTicketGuidelines-1.0.0.dist-info/metadata.json
TracTicketGuidelines-1.0.0.dist-info/top_level.txt
ticketguidelines/__init__.py
ticketguidelines/web_ui.py
ticketguidelines/htdocs/main.css
