Metadata-Version: 2.0
Name: TracTicketGuidelines
Version: 1.0.0
Summary: Adds your ticket guidelines to the ticket view. The guidelines are specified in the wiki pages 'TicketGuidelines/NewShort' and 'TicketGuidelines/ModifyShort'.
Home-page: https://trac-hacks.org/wiki/TicketGuidelinesPlugin
Author: Sebastian Krysmanski
Author-email: UNKNOWN
License: Modified BSD
Keywords: trac plugin
Platform: UNKNOWN
Requires-Dist: Trac
